[
  {
    "rootID": "20240208162706-jkmh8j9",
    "icon": "",
    "title": "UG1L5——图片绘制和框"
  },
  {
    "rootID": "20240308190703-v6cen7d",
    "icon": "",
    "title": "UN2L5——分包、黏包"
  },
  {
    "rootID": "20231114124407-x1fjjv2",
    "icon": "",
    "title": "UMVCL11——MVE基本实例"
  },
  {
    "rootID": "20231114200140-ry5n8z9",
    "icon": "",
    "title": "UMVCSL3——Model和Proxy"
  },
  {
    "rootID": "20231124131216-hqx8nbh",
    "icon": "",
    "title": "UG4L7-2——UIPanel加载界面"
  },
  {
    "rootID": "20230712211009-ys55mha",
    "icon": "1f4fa",
    "title": "UG1——IMGUI系列"
  },
  {
    "rootID": "20240330222422-z2friqz",
    "icon": "2615",
    "title": "UM2——Java"
  },
  {
    "rootID": "20240321152428-p3c1ha4",
    "icon": "1f4f2",
    "title": "UM——Unity移动平台相关"
  },
  {
    "rootID": "20240201183701-fdd41bp",
    "icon": "23-fe0f-20e3",
    "title": "CS——CSharp笔记"
  },
  {
    "rootID": "20240302205751-zqsapys",
    "icon": "1f310",
    "title": "UN——Unity网络开发相关"
  },
  {
    "rootID": "20231121212338-j3dm0ck",
    "icon": "2615",
    "title": "UH——Unity热更新笔记"
  },
  {
    "rootID": "20240208133204-oq28gqs",
    "icon": "1f4fa",
    "title": "UG——UI系统笔记"
  },
  {
    "rootID": "20231029225256-pnki455",
    "icon": "",
    "title": "CS5L5——CSharp版本和Unity的关系"
  },
  {
    "rootID": "20230811200418-p1cw6gs",
    "icon": "23-fe0f-20e3",
    "title": "CS1——CSharp入门系列"
  },
  {
    "rootID": "20230822141111-24xrhqx",
    "icon": "23-fe0f-20e3",
    "title": "CS3——CSharp核心系列"
  },
  {
    "rootID": "20230822140820-zpoyztw",
    "icon": "23-fe0f-20e3",
    "title": "CS2——CSharp基础系列"
  },
  {
    "rootID": "20230822141134-a4mua9i",
    "icon": "23-fe0f-20e3",
    "title": "CS4——CSharp进阶系列"
  },
  {
    "rootID": "20230822144423-x5zm58f",
    "icon": "",
    "title": "U1L0-3——Unity工作原理"
  },
  {
    "rootID": "20230822032646-7gj69u7",
    "icon": "",
    "title": "U1L0-1——Unity环境搭建"
  },
  {
    "rootID": "20240625114859-ag9w64z",
    "icon": "",
    "title": "US3S1L2——兰伯特光照模型"
  },
  {
    "rootID": "20240625211637-iw1n08i",
    "icon": "",
    "title": "US3S1L4-2——Phong式高光反射模型的逐片元光照"
  },
  {
    "rootID": "20240625170147-7xe5112",
    "icon": "",
    "title": "US3S1L3——半兰伯特光照模型"
  },
  {
    "rootID": "20240625181412-8cwmr65",
    "icon": "",
    "title": "US3S1L4——Phong式高光反射模型"
  },
  {
    "rootID": "20240510154100-bdihg1e",
    "icon": "",
    "title": "US1L8——其他相关必备概念"
  },
  {
    "rootID": "20240510140425-xh54sqa",
    "icon": "1f3a8",
    "title": "US1——Shader必备概念"
  },
  {
    "rootID": "20240510154856-titgvox",
    "icon": "1f3a8",
    "title": "US2——Shader必备基础"
  },
  {
    "rootID": "20230808223127-rmqmu7b",
    "icon": "",
    "title": "U3L18——3D动画相关"
  },
  {
    "rootID": "20230614152217-l54am5n",
    "icon": "",
    "title": "CS1L1——CSharp程序的基本结构"
  }
]